newrelic/__init__.py
newrelic/alert/__init__.py
newrelic/alert/channels.py
newrelic/alert/condition.py
newrelic/alert/destinations.py
newrelic/alert/policy.py
newrelic/alert/workflows.py
newrelic/cli/args.py
newrelic/cli/entrypoint.py
newrelic/nerdgraph/alert/channels.py
newrelic/nerdgraph/alert/condition.py
newrelic/nerdgraph/alert/destinations.py
newrelic/nerdgraph/alert/policy.py
newrelic/nerdgraph/alert/workflows.py
newrelic/nerdgraph/client.py
newrelic/nerdgraph/synthetic/scripted_browser.py
newrelic/nerdgraph/synthetic/secure_credential.py
newrelic/nerdgraph/synthetic/service_level.py
newrelic/synthetic/__init__.py
newrelic/synthetic/scripted_browser.py
newrelic/synthetic/secure_credential.py
newrelic/synthetic/service_level.py
newrelic/utils/config.py
newrelic/utils/log.py
newrelic_synthetic_python_client-0.4.0.dist-info/LICENSE
newrelic_synthetic_python_client-0.4.0.dist-info/METADATA
newrelic_synthetic_python_client-0.4.0.dist-info/WHEEL
newrelic_synthetic_python_client-0.4.0.dist-info/entry_points.txt
newrelic_synthetic_python_client-0.4.0.dist-info/RECORD
