Metadata-Version: 2.1
Name: newrelic-synthetic-python-client
Version: 0.4.0
Summary: NewRelic CLI
Home-page: https://github.com/Drinkey/newrelic-synthetic-python-client
Author: Junkai Zhang
Author-email: drink3y@gmail.com
Requires-Python: >=3.8,<4.0
Classifier: Programming Language :: Python :: 3
Classifier: Programming Language :: Python :: 3.8
Classifier: Programming Language :: Python :: 3.9
Classifier: Programming Language :: Python :: 3.10
Classifier: Programming Language :: Python :: 3.11
Requires-Dist: loguru (>=0.6.0,<0.7.0)
Requires-Dist: requests (>=2.28.1,<3.0.0)
Project-URL: Repository, https://github.com/Drinkey/newrelic-synthetic-python-client
